docs/index.md
timebombs/__init__.py
timebombs/__main__.py
timebombs-0.1.0.dist-info/METADATA
timebombs-0.1.0.dist-info/WHEEL
timebombs-0.1.0.dist-info/entry_points.txt
timebombs-0.1.0.dist-info/RECORD
