Metadata-Version: 2.1
Name: timebombs
Version: 0.1.0
Summary: A small package to keep tech debt to a minimum.
Home-page: https://github.com/mattmezza/timebombs
Keywords: CI,continuous integration,tech debt
Author: Matteo Merola
Requires-Python: >=3.9,<4.0
Classifier: Development Status :: 4 - Beta
Classifier: Intended Audience :: Developers
Classifier: Intended Audience :: Information Technology
Classifier: Intended Audience :: System Administrators
Classifier: License :: OSI Approved :: MIT License
Classifier: Operating System :: OS Independent
Classifier: Programming Language :: Python
Classifier: Programming Language :: Python :: 3
Classifier: Programming Language :: Python :: 3.9
Classifier: Programming Language :: Python :: 3.10
Classifier: Programming Language :: Python :: 3.11
Classifier: Programming Language :: Python :: 3.12
Classifier: Programming Language :: Python :: 3 :: Only
Classifier: Topic :: Software Development
Classifier: Topic :: Software Development :: Libraries
Classifier: Topic :: Software Development :: Libraries :: Python Modules
Classifier: Typing :: Typed
Requires-Dist: pytz (>=2024.1,<2025.0)
Requires-Dist: typer (>=0.12.3,<0.13.0)
Project-URL: Documentation, https://matteo.merola.co/timebombs
Project-URL: Repository, https://github.com/mattmezza/timebombs
